{
    "top_champions": {
      "iron":{
        "top": ["Urgot", "Nasus", "Jax", "Rumble", "Garen"],
        "jg": ["Amumu", "Vi", "Volibear","Jax","Rammus"],
        "mid": ["Malzahar", "Veigar", "Ahri", "Yasuo", "Brand"],
        "adc": ["MissFortune", "Sivir", "Jinx", "Caitlyn", "Xayah"],
        "sup": ["Nautilus", "Taric", "Sona", "Nami", "Bard"]
      },
      "bronze":{
        "top": ["Yorick", "Garen", "Nasus", "Urgot", "Mordekaiser"],
        "jg": ["Skarner", "Amumu", "Volibear","Vi","Rammus"],
        "mid": ["Malzahar", "Velkoz", "Brand", "Fizz", "Ahri"],
        "adc": ["Sivir", "Jinx", "MissFortune", "Ashe", "KogMaw"],
        "sup": ["Velkoz", "Sona", "Taric", "Brand", "Nami"]
      },
      "silver":{
        "top":["Yorick", "Garen", "Nasus", "Urgot", "Mordekaiser"],
        "jg":["Amumu", "Volibear", "Nunu","Vi","Warwick"],
        "mid":["Malzahar", "Lux", "Velkoz", "Veigar", "Brand"],
        "adc": ["Sivir", "Jinx", "MissFortune", "Ashe", "KogMaw"],
        "sup": ["Sona", "Janna", "Velkoz", "Zilean", "Nami"]
      },
      "gold":{
        "top":["Yorick", "Garen", "Kayle", "Mordekaiser", "Urgot"],
        "jg":["Nunu", "Amumu", "Volibear","Vi","Warwick"],
        "mid":["Malzahar", "Ahri", "Lux", "Anivia", "Veigar"],
        "adc": ["Jinx", "Sivir", "Ashe", "MissFortune", "KogMaw"],
        "sup": ["Sona", "Janna", "Nami", "Zilean", "Soraka"]
      },
      "platinum":{
        "top":["Yorick", "Mordekaiser", "Garen", "Tahm Kench", "Karma"],
        "jg":["Nunu", "Vi", "Amumu","Hecarim","Warwick"],
        "mid":["Malzahar", "Ahri", "Lux", "Velkoz", "Anivia"],
        "adc": ["Jinx", "Sivir", "KogMaw", "MissFortune", "Ashe"],
        "sup": ["Sona", "Janna", "Nami", "Velkoz", "Soraka"]
      },
      "diamond":{
        "top":["Kled", "Yorick", "Singed", "Kennen", "Karma"],
        "jg":["Nunu", "Vi", "Shaco", "Udyr","Hecarim"],
        "mid":["Malzahar", "Ahri", "Velkoz", "Katarina", "Zed"],
        "adc": ["Jinx", "Sivir", "Vayne", "Draven", "Xayah"],
        "sup": ["Sona", "Zilean", "Velkoz", "Nami", "Soraka"]
      }
    },
    "buffs": [
      "La pasiva de Illaoi (Profeta de un Dios Ancestral) ahora tambien escala con Poder de habilidad. Tambien Dura Lección recibio una tasa de daño mínimo",
      "Sylas obtuvo un incremento en su daño y vida base. Matarreyes ahora tiene un mayor daño básico"
    ],
    "nerfs": [
      "El rebote de sivir cuenta mas maná. El crecimiento de vida y regeneración de mana disminuyeron"
    ],
    "updates": [
      "Cambios en la jugabilidad de Illaoi, se pulió el kit, tanto su pasiva como sus habilidades.",
      "Las habilidades de Udyr se podran subir de nivel hasta 6 veces"
    ]
  }
